[
  {
    "id": 799,
    "ward_Num": 10,
    "mun_Name": "Phungling",
    "munId": 6,
    "disId": 1,
    "provinceId": 1
  },
  {
    "id": 798,
    "ward_Num": 1,
    "mun_Name": "Phungling",
    "munId": 6,
    "disId": 1,
    "provinceId": 1
  },
  {
    "id": 797,
    "ward_Num": 6,
    "mun_Name": "Phungling",
    "munId": 6,
    "disId": 1,
    "provinceId": 1
  },
  {
    "id": 796,
    "ward_Num": 5,
    "mun_Name": "Phungling",
    "munId": 6,
    "disId": 1,
    "provinceId": 1
  },
  {
    "id": 795,
    "ward_Num": 4,
    "mun_Name": "Phungling",
    "munId": 6,
    "disId": 1,
    "provinceId": 1
  },
  {
    "id": 794,
    "ward_Num": 3,
    "mun_Name": "Phungling",
    "munId": 6,
    "disId": 1,
    "provinceId": 1
  },
  {
    "id": 793,
    "ward_Num": 2,
    "mun_Name": "Phungling",
    "munId": 6,
    "disId": 1,
    "provinceId": 1
  },
  {
    "id": 791,
    "ward_Num": 11,
    "mun_Name": "Phungling",
    "munId": 6,
    "disId": 1,
    "provinceId": 1
  },
  {
    "id": 769,
    "ward_Num": 9,
    "mun_Name": "Phungling",
    "munId": 6,
    "disId": 1,
    "provinceId": 1
  },
  {
    "id": 767,
    "ward_Num": 8,
    "mun_Name": "Phungling",
    "munId": 6,
    "disId": 1,
    "provinceId": 1
  },
  {
    "id": 766,
    "ward_Num": 7,
    "mun_Name": "Phungling",
    "munId": 6,
    "disId": 1,
    "provinceId": 1
  }
]